{
  "data": [
    {
      "date": "2026-04-09",
      "signals": 4,
      "avg_return": 62.1,
      "avg_peak": 133.4,
      "win_rate": 50.0,
      "total_return": 248.6,
      "total_peak": 533.6
    },
    {
      "date": "2026-04-10",
      "signals": 13,
      "avg_return": 214.3,
      "avg_peak": 315.6,
      "win_rate": 77.0,
      "total_return": 2785.4,
      "total_peak": 4102.5
    },
    {
      "date": "2026-04-13",
      "signals": 14,
      "avg_return": 199.3,
      "avg_peak": 299.3,
      "win_rate": 79.0,
      "total_return": 2790.9,
      "total_peak": 4190.7
    },
    {
      "date": "2026-04-14",
      "signals": 19,
      "avg_return": 170.3,
      "avg_peak": 268.6,
      "win_rate": 79.0,
      "total_return": 3236.6,
      "total_peak": 5102.5
    },
    {
      "date": "2026-04-15",
      "signals": 22,
      "avg_return": 173.4,
      "avg_peak": 260.2,
      "win_rate": 73.0,
      "total_return": 3815.7,
      "total_peak": 5723.9
    }
  ],
  "signals": [
    {
      "ticker": "CRWV",
      "date": "2026-04-09",
      "pnl": 262.0,
      "peak": 319.0,
      "status": "open"
    },
    {
      "ticker": "AMZN",
      "date": "2026-04-09",
      "pnl": 101.1,
      "peak": 166.2,
      "status": "closed"
    },
    {
      "ticker": "PLTR",
      "date": "2026-04-09",
      "pnl": -64.7,
      "peak": -16.2,
      "status": "closed"
    },
    {
      "ticker": "SLV",
      "date": "2026-04-09",
      "pnl": -49.8,
      "peak": 64.6,
      "status": "closed"
    },
    {
      "ticker": "INTC",
      "date": "2026-04-10",
      "pnl": 165.2,
      "peak": 181.4,
      "status": "closed"
    },
    {
      "ticker": "SNDK",
      "date": "2026-04-10",
      "pnl": 40.3,
      "peak": 138.1,
      "status": "closed"
    },
    {
      "ticker": "NBIS",
      "date": "2026-04-10",
      "pnl": 347.9,
      "peak": 421.2,
      "status": "closed"
    },
    {
      "ticker": "AMZN",
      "date": "2026-04-10",
      "pnl": 216.9,
      "peak": 349.4,
      "status": "closed"
    },
    {
      "ticker": "CRWV",
      "date": "2026-04-10",
      "pnl": 219.7,
      "peak": 256.4,
      "status": "open"
    },
    {
      "ticker": "SOXL",
      "date": "2026-04-10",
      "pnl": 287.4,
      "peak": 287.4,
      "status": "closed"
    },
    {
      "ticker": "WULF",
      "date": "2026-04-10",
      "pnl": -20.0,
      "peak": 84.7,
      "status": "closed"
    },
    {
      "ticker": "INTC",
      "date": "2026-04-10",
      "pnl": 779.1,
      "peak": 816.3,
      "status": "closed"
    },
    {
      "ticker": "MU",
      "date": "2026-04-10",
      "pnl": 500.3,
      "peak": 1034.0,
      "status": "closed"
    },
    {
      "ticker": "MRVL",
      "date": "2026-04-13",
      "pnl": 5.5,
      "peak": 88.2,
      "status": "closed"
    },
    {
      "ticker": "SNDK",
      "date": "2026-04-14",
      "pnl": -55.9,
      "peak": 0.0,
      "status": "closed"
    },
    {
      "ticker": "ORCL",
      "date": "2026-04-14",
      "pnl": 164.1,
      "peak": 334.6,
      "status": "closed"
    },
    {
      "ticker": "CRWV",
      "date": "2026-04-14",
      "pnl": 50.7,
      "peak": 91.3,
      "status": "open"
    },
    {
      "ticker": "BE",
      "date": "2026-04-14",
      "pnl": 243.3,
      "peak": 397.7,
      "status": "closed"
    },
    {
      "ticker": "NBIS",
      "date": "2026-04-14",
      "pnl": 43.5,
      "peak": 88.2,
      "status": "open"
    },
    {
      "ticker": "NVDA",
      "date": "2026-04-15",
      "pnl": -4.7,
      "peak": 3.8,
      "status": "open"
    },
    {
      "ticker": "GLD",
      "date": "2026-04-15",
      "pnl": -51.1,
      "peak": -21.3,
      "status": "closed"
    },
    {
      "ticker": "MSFT",
      "date": "2026-04-15",
      "pnl": 634.9,
      "peak": 638.9,
      "status": "open"
    }
  ],
  "total": 22,
  "avg_return": 173.4,
  "avg_peak": 260.2,
  "win_rate": 73.0,
  "generated": "2026-04-16T08:22:16.869833"
}